{
    "act": 4,
    "name": "THE VIEW",
    "flow": [
        { "type": "title_card", "title": "ACT IV", "subtitle": "THE VIEW" },
        { "type": "planning", "day": 1 },
        { "type": "moment", "id": "act4_day1_slot1" },
        { "type": "moment", "id": "act4_day1_slot2" },
        { "type": "moment", "id": "act4_day1_slot3" },
        { "type": "moment", "id": "act4_day1_slot4" },
        { "type": "day_end" },
        { "type": "mirror_moment" },
        { "type": "planning", "day": 2 },
        { "type": "moment", "id": "act4_day2_slot1" },
        { "type": "moment", "id": "act4_day2_slot2" },
        { "type": "moment", "id": "act4_day2_slot3" },
        { "type": "moment", "id": "act4_day2_slot4" },
        { "type": "day_end" },
        { "type": "planning", "day": 3 },
        { "type": "moment", "id": "act4_day3_slot1" },
        { "type": "moment", "id": "act4_day3_slot2" },
        { "type": "moment", "id": "act4_day3_slot3" },
        { "type": "moment", "id": "act4_day3_slot4" },
        { "type": "day_end" },
        { "type": "mirror_moment" },
        { "type": "planning", "day": 4 },
        { "type": "moment", "id": "act4_day4_slot1" },
        { "type": "moment", "id": "act4_day4_slot2" },
        { "type": "moment", "id": "act4_day4_slot3" },
        { "type": "moment", "id": "act4_day4_slot4" },
        { "type": "day_end" },
        { "type": "climax", "id": "act4_ultimate_promotion" },
        { "type": "act_transition", "nextAct": 5 }
    ]
}
